[
  {
    "Item ID": "001",
    "img": "./img/images/images/wheat.png",
    "Item Name": "Wheat",
    "Category": "Crop",
    "Unit Price (Gems)": "1",
    "Sales Volume (Month)": "2000",
    "Lead Time (Days)": "3",
    "Reorder Quantity": "1500",
    "Inventory Level": "1800",
    "Restocking": "0"
  },
  {
    "Item ID": "002",
    "img": "./img/images/images/carrot.png",
    "Item Name": "Carrot",
    "Category": "Crop",
    "Unit Price (Gems)": "1",
    "Sales Volume (Month)": "1500",
    "Lead Time (Days)": "2",
    "Reorder Quantity": "1000",
    "Inventory Level": "1200",
    "Restocking": "0"
  },
  {
    "Item ID": "003",
    "img": "./img/images/images/potato.png",
    "Item Name": "Potato",
    "Category": "Crop",
    "Unit Price (Gems)": "1",
    "Sales Volume (Month)": "1800",
    "Lead Time (Days)": "2",
    "Reorder Quantity": "1200",
    "Inventory Level": "1500",
    "Restocking": "0"
  },
  {
    "Item ID": "004",
    "img": "./img/images/images/pumpkin.png",
    "Item Name": "Pumpkin",
    "Category": "Crop",
    "Unit Price (Gems)": "2",
    "Sales Volume (Month)": "800",
    "Lead Time (Days)": "4",
    "Reorder Quantity": "500",
    "Inventory Level": "600",
    "Restocking": "0"
  },
  {
    "Item ID": "005",
    "img": "./img/images/images/melon.png",
    "Item Name": "Melon",
    "Category": "Crop",
    "Unit Price (Gems)": "2",
    "Sales Volume (Month)": "900",
    "Lead Time (Days)": "3",
    "Reorder Quantity": "600",
    "Inventory Level": "700",
    "Restocking": "0"
  },
  {
    "Item ID": "006",
    "img": "./img/images/images/Wheat.png",
    "Item Name": "wheat",
    "Category": "Crop",
    "Unit Price (Gems)": "1",
    "Sales Volume (Month)": "2500",
    "Lead Time (Days)": "1",
    "Reorder Quantity": "2000",
    "Inventory Level": "2300",
    "Restocking": "0"
  },
  {
    "Item ID": "007",
    "img": "./img/images/images/beetroot.png",
    "Item Name": "Beetroot",
    "Category": "Crop",
    "Unit Price (Gems)": "2",
    "Sales Volume (Month)": "1000",
    "Lead Time (Days)": "2",
    "Reorder Quantity": "700",
    "Inventory Level": "800",
    "Restocking": "0"
  },
  {
    "Item ID": "008",
    "img": "./img/images/images/cocoa beans.png",
    "Item Name": "Cocoa Beans",
    "Category": "Crop",
    "Unit Price (Gems)": "3",
    "Sales Volume (Month)": "500",
    "Lead Time (Days)": "3",
    "Reorder Quantity": "400",
    "Inventory Level": "450",
    "Restocking": "0"
  },
  {
    "Item ID": "009",
    "img": "./img/images/images/bread.png",
    "Item Name": "Bread",
    "Category": "Food",
    "Unit Price (Gems)": "3",
    "Sales Volume (Month)": "1200",
    "Lead Time (Days)": "2",
    "Reorder Quantity": "800",
    "Inventory Level": "900",
    "Restocking": "0"
  },
  {
    "Item ID": "010",
    "img": "./img/images/images/apple.png",
    "Item Name": "Apple",
    "Category": "Food",
    "Unit Price (Gems)": "2",
    "Sales Volume (Month)": "1000",
    "Lead Time (Days)": "1",
    "Reorder Quantity": "700",
    "Inventory Level": "800",
    "Restocking": "0"
  },
  {
    "Item ID": "011",
    "img": "./img/images/images/cooked beef.png",
    "Item Name": "Cooked Beef",
    "Category": "Food",
    "Unit Price (Gems)": "5",
    "Sales Volume (Month)": "600",
    "Lead Time (Days)": "1",
    "Reorder Quantity": "400",
    "Inventory Level": "500",
    "Restocking": "0"
  },
  {
    "Item ID": "012",
    "img": "./img/images/images/cooked porkchop.png",
    "Item Name": "Cooked Porkchop",
    "Category": "Food",
    "Unit Price (Gems)": "5",
    "Sales Volume (Month)": "600",
    "Lead Time (Days)": "1",
    "Reorder Quantity": "400",
    "Inventory Level": "500",
    "Restocking": "0"
  },
  {
    "Item ID": "013",
    "img": "./img/images/images/cooked chicken.png",
    "Item Name": "Cooked Chicken",
    "Category": "Food",
    "Unit Price (Gems)": "4",
    "Sales Volume (Month)": "700",
    "Lead Time (Days)": "1",
    "Reorder Quantity": "500",
    "Inventory Level": "600",
    "Restocking": "0"
  },
  {
    "Item ID": "014",
    "img": "./img/images/images/baked potato.png",
    "Item Name": "Baked Potato",
    "Category": "Food",
    "Unit Price (Gems)": "2",
    "Sales Volume (Month)": "800",
    "Lead Time (Days)": "1",
    "Reorder Quantity": "600",
    "Inventory Level": "700",
    "Restocking": "0"
  },
  {
    "Item ID": "015",
    "img": "./img/images/images/carrot on a stick.png",
    "Item Name": "Carrot on a Stick",
    "Category": "Tool",
    "Unit Price (Gems)": "10",
    "Sales Volume (Month)": "300",
    "Lead Time (Days)": "2",
    "Reorder Quantity": "200",
    "Inventory Level": "250",
    "Restocking": "0"
  },
  {
    "Item ID": "016",
    "img": "./img/images/images/pumpkin pie.png",
    "Item Name": "Pumpkin Pie",
    "Category": "Food",
    "Unit Price (Gems)": "6",
    "Sales Volume (Month)": "500",
    "Lead Time (Days)": "2",
    "Reorder Quantity": "350",
    "Inventory Level": "400",
    "Restocking": "0"
  },
  {
    "Item ID": "017",
    "img": "./img/images/images/golden carrot.png",
    "Item Name": "Golden Carrot",
    "Category": "Food",
    "Unit Price (Gems)": "8",
    "Sales Volume (Month)": "400",
    "Lead Time (Days)": "2",
    "Reorder Quantity": "300",
    "Inventory Level": "350",
    "Restocking": "0"
  },
  {
    "Item ID": "018",
    "img": "./img/images/images/glow berries.png",
    "Item Name": "Glow Berries",
    "Category": "Crop",
    "Unit Price (Gems)": "3",
    "Sales Volume (Month)": "400",
    "Lead Time (Days)": "1",
    "Reorder Quantity": "250",
    "Inventory Level": "300",
    "Restocking": "0"
  },
  {
    "Item ID": "019",
    "img": "./img/images/images/honey bottle.png",
    "Item Name": "Honey Bottle",
    "Category": "Food",
    "Unit Price (Gems)": "4",
    "Sales Volume (Month)": "350",
    "Lead Time (Days)": "1",
    "Reorder Quantity": "200",
    "Inventory Level": "250",
    "Restocking": "0"
  },
  {
    "Item ID": "020",
    "img": "./img/images/images/beehive.png",
    "Item Name": "Beehive",
    "Category": "Block",
    "Unit Price (Gems)": "25",
    "Sales Volume (Month)": "100",
    "Lead Time (Days)": "7",
    "Reorder Quantity": "80",
    "Inventory Level": "90",
    "Restocking": "1"
  },
  {
    "Item ID": "021",
    "img": "./img/images/images/hay bale.png",
    "Item Name": "Hay Bale",
    "Category": "Block",
    "Unit Price (Gems)": "3",
    "Sales Volume (Month)": "600",
    "Lead Time (Days)": "2",
    "Reorder Quantity": "450",
    "Inventory Level": "500",
    "Restocking": "0"
  },
  {
    "Item ID": "022",
    "img": "./img/images/images/cake.png",
    "Item Name": "Cake",
    "Category": "Food",
    "Unit Price (Gems)": "10",
    "Sales Volume (Month)": "200",
    "Lead Time (Days)": "3",
    "Reorder Quantity": "150",
    "Inventory Level": "180",
    "Restocking": "0"
  },
  {
    "Item ID": "023",
    "img": "./img/images/images/Enchanted Golden Apple.png",
    "Item Name": "Enchanted Golden Apple",
    "Category": "Food",
    "Unit Price (Gems)": "50",
    "Sales Volume (Month)": "50",
    "Lead Time (Days)": "30",
    "Reorder Quantity": "30",
    "Inventory Level": "40",
    "Restocking": "1"
  },
  {
    "Item ID": "024",
    "img": "./img/images/images/Bread2.png",
    "Item Name": "Bread",
    "Category": "Food",
    "Unit Price (Gems)": "3",
    "Sales Volume (Month)": "1200",
    "Lead Time (Days)": "2",
    "Reorder Quantity": "800",
    "Inventory Level": "900",
    "Restocking": "0"
  },
  {
    "Item ID": "025",
    "img": "./img/images/images/Mushroom Stew.png",
    "Item Name": "Mushroom Stew",
    "Category": "Food",
    "Unit Price (Gems)": "4",
    "Sales Volume (Month)": "500",
    "Lead Time (Days)": "2",
    "Reorder Quantity": "300",
    "Inventory Level": "350",
    "Restocking": "0"
  },
  {
    "Item ID": "026",
    "img": "./img/images/images/Orange.png",
    "Item Name": "Orange",
    "Category": "Food",
    "Unit Price (Gems)": "2",
    "Sales Volume (Month)": "700",
    "Lead Time (Days)": "1",
    "Reorder Quantity": "500",
    "Inventory Level": "600",
    "Restocking": "0"
  },
  {
    "Item ID": "027",
    "img": "./img/images/images/Golden Apple.png",
    "Item Name": "Golden Apple",
    "Category": "Food",
    "Unit Price (Gems)": "15",
    "Sales Volume (Month)": "200",
    "Lead Time (Days)": "3",
    "Reorder Quantity": "150",
    "Inventory Level": "180",
    "Restocking": "0"
  },
  {
    "Item ID": "028",
    "img": "./img/images/images/Pufferfish.png",
    "Item Name": "Pufferfish",
    "Category": "Food",
    "Unit Price (Gems)": "8",
    "Sales Volume (Month)": "300",
    "Lead Time (Days)": "2",
    "Reorder Quantity": "200",
    "Inventory Level": "250",
    "Restocking": "0"
  },
  {
    "Item ID": "029",
    "img": "./img/images/images/Bananna.png",
    "Item Name": "Banana",
    "Category": "Food",
    "Unit Price (Gems)": "8",
    "Sales Volume (Month)": "300",
    "Lead Time (Days)": "2",
    "Reorder Quantity": "200",
    "Inventory Level": "250",
    "Restocking": "0"
  },
  {
    "Item ID": "030",
    "img": "./img/images/images/Raw Beef.png",
    "Item Name": "Raw Beef",
    "Category": "Food",
    "Unit Price (Gems)": "2",
    "Sales Volume (Month)": "1000",
    "Lead Time (Days)": "1",
    "Reorder Quantity": "700",
    "Inventory Level": "800",
    "Restocking": "0"
  },
  {
    "Item ID": "031",
    "img": "./img/images/images/Raw Porkchop.png",
    "Item Name": "Raw Porkchop",
    "Category": "Food",
    "Unit Price (Gems)": "2",
    "Sales Volume (Month)": "1000",
    "Lead Time (Days)": "1",
    "Reorder Quantity": "700",
    "Inventory Level": "800",
    "Restocking": "0"
  },
  {
    "Item ID": "032",
    "img": "./img/images/images/Raw Chicken.png",
    "Item Name": "Raw Chicken",
    "Category": "Food",
    "Unit Price (Gems)": "1",
    "Sales Volume (Month)": "1200",
    "Lead Time (Days)": "1",
    "Reorder Quantity": "800",
    "Inventory Level": "900",
    "Restocking": "0"
  },
  {
    "Item ID": "033",
    "img": "./img/images/images/Raw Mutton.png",
    "Item Name": "Raw Mutton",
    "Category": "Food",
    "Unit Price (Gems)": "2",
    "Sales Volume (Month)": "800",
    "Lead Time (Days)": "1",
    "Reorder Quantity": "600",
    "Inventory Level": "700",
    "Restocking": "0"
  },
  {
    "Item ID": "034",
    "img": "./img/images/images/Raw Cod.png",
    "Item Name": "Raw Cod",
    "Category": "Food",
    "Unit Price (Gems)": "1",
    "Sales Volume (Month)": "1500",
    "Lead Time (Days)": "1",
    "Reorder Quantity": "1000",
    "Inventory Level": "1200",
    "Restocking": "0"
  },
  {
    "Item ID": "035",
    "img": "./img/images/images/Raw Salmon.png",
    "Item Name": "Raw Salmon",
    "Category": "Food",
    "Unit Price (Gems)": "2",
    "Sales Volume (Month)": "800",
    "Lead Time (Days)": "1",
    "Reorder Quantity": "600",
    "Inventory Level": "700",
    "Restocking": "0"
  },
  {
    "Item ID": "036",
    "img": "./img/images/images/Tropical Fish.png",
    "Item Name": "Tropical Fish",
    "Category": "Food",
    "Unit Price (Gems)": "2",
    "Sales Volume (Month)": "700",
    "Lead Time (Days)": "1",
    "Reorder Quantity": "500",
    "Inventory Level": "600",
    "Restocking": "0"
  },
  {
    "Item ID": "037",
    "img": "./img/images/images/Sea Pickle.png",
    "Item Name": "Sea Pickle",
    "Category": "Crop",
    "Unit Price (Gems)": "2",
    "Sales Volume (Month)": "600",
    "Lead Time (Days)": "1",
    "Reorder Quantity": "400",
    "Inventory Level": "500",
    "Restocking": "0"
  },
  {
    "Item ID": "038",
    "img": "./img/images/images/Bamboo.png",
    "Item Name": "Bamboo",
    "Category": "Crop",
    "Unit Price (Gems)": "2",
    "Sales Volume (Month)": "1200",
    "Lead Time (Days)": "1",
    "Reorder Quantity": "800",
    "Inventory Level": "900",
    "Restocking": "0"
  },
  {
    "Item ID": "039",
    "img": "./img/images/images/Cactus.png",
    "Item Name": "Cactus",
    "Category": "Crop",
    "Unit Price (Gems)": "1",
    "Sales Volume (Month)": "1800",
    "Lead Time (Days)": "1",
    "Reorder Quantity": "1200",
    "Inventory Level": "1500",
    "Restocking": "0"
  },
  {
    "Item ID": "040",
    "img": "./img/images/images/Sugar.png",
    "Item Name": "Sugar",
    "Category": "Ingredient",
    "Unit Price (Gems)": "2",
    "Sales Volume (Month)": "1300",
    "Lead Time (Days)": "1",
    "Reorder Quantity": "900",
    "Inventory Level": "1000",
    "Restocking": "0"
  },
  {
    "Item ID": "041",
    "img": "./img/images/images/Pumpkin Seeds.png",
    "Item Name": "Pumpkin Seeds",
    "Category": "Crop",
    "Unit Price (Gems)": "1",
    "Sales Volume (Month)": "1600",
    "Lead Time (Days)": "1",
    "Reorder Quantity": "1100",
    "Inventory Level": "1300",
    "Restocking": "0"
  },
  {
    "Item ID": "042",
    "img": "./img/images/images/Melon Seeds.png",
    "Item Name": "Melon Seeds",
    "Category": "Crop",
    "Unit Price (Gems)": "1",
    "Sales Volume (Month)": "1700",
    "Lead Time (Days)": "1",
    "Reorder Quantity": "1100",
    "Inventory Level": "1300",
    "Restocking": "0"
  },
  {
    "Item ID": "043",
    "img": "./img/images/images/Wheat Seeds.png",
    "Item Name": "Wheat Seeds",
    "Category": "Crop",
    "Unit Price (Gems)": "1",
    "Sales Volume (Month)": "2000",
    "Lead Time (Days)": "1",
    "Reorder Quantity": "1400",
    "Inventory Level": "1600",
    "Restocking": "0"
  },
  {
    "Item ID": "044",
    "img": "./img/images/images/Beetroot Seeds.png",
    "Item Name": "Beetroot Seeds",
    "Category": "Crop",
    "Unit Price (Gems)": "1",
    "Sales Volume (Month)": "1500",
    "Lead Time (Days)": "1",
    "Reorder Quantity": "1000",
    "Inventory Level": "1200",
    "Restocking": "0"
  },
  {
    "Item ID": "045",
    "img": "./img/images/images/Potato Seeds.png",
    "Item Name": "Potato Seeds",
    "Category": "Crop",
    "Unit Price (Gems)": "1",
    "Sales Volume (Month)": "1600",
    "Lead Time (Days)": "1",
    "Reorder Quantity": "1100",
    "Inventory Level": "1300",
    "Restocking": "0"
  },
  {
    "Item ID": "046",
    "img": "./img/images/images/Carrot Seeds.png",
    "Item Name": "Carrot Seeds",
    "Category": "Crop",
    "Unit Price (Gems)": "1",
    "Sales Volume (Month)": "1600",
    "Lead Time (Days)": "1",
    "Reorder Quantity": "1100",
    "Inventory Level": "1300",
    "Restocking": "0"
  },
  {
    "Item ID": "047",
    "img": "./img/images/images/Cocoa Beans Seeds.png",
    "Item Name": "Cocoa Beans Seeds",
    "Category": "Crop",
    "Unit Price (Gems)": "2",
    "Sales Volume (Month)": "800",
    "Lead Time (Days)": "2",
    "Reorder Quantity": "600",
    "Inventory Level": "700",
    "Restocking": "0"
  },
  {
    "Item ID": "048",
    "img": "./img/images/images/Sweet Berries.png",
    "Item Name": "Sweet Berries",
    "Category": "Crop",
    "Unit Price (Gems)": "1",
    "Sales Volume (Month)": "1400",
    "Lead Time (Days)": "1",
    "Reorder Quantity": "900",
    "Inventory Level": "1000",
    "Restocking": "0"
  },
  {
    "Item ID": "049",
    "img": "./img/images/images/Orange.png",
    "Item Name": "Oranges",
    "Category": "Crop",
    "Unit Price (Gems)": "5",
    "Sales Volume (Month)": "1700",
    "Lead Time (Days)": "1",
    "Reorder Quantity": "800",
    "Inventory Level": "900",
    "Restocking": "0"
  },
  {
    "Item ID": "050",
    "img": "./img/images/images/Seagrass.png",
    "Item Name": "Seagrass",
    "Category": "Crop",
    "Unit Price (Gems)": "2",
    "Sales Volume (Month)": "1200",
    "Lead Time (Days)": "1",
    "Reorder Quantity": "800",
    "Inventory Level": "900",
    "Restocking": "0"
  }
]